mcdm/__init__.py
mcdm/ahp.py
mcdm/electre.py
mcdm/merec.py
mcdm/normalization.py
mcdm/swara.py
mcdm/topsis.py
mcdmtools-0.0.27.dist-info/LICENSE
mcdmtools-0.0.27.dist-info/METADATA
mcdmtools-0.0.27.dist-info/WHEEL
mcdmtools-0.0.27.dist-info/top_level.txt
mcdmtools-0.0.27.dist-info/RECORD
